[

  {
    "id": "4198914_",
    "nombre": "St. Truiden vs Zulte Waregem",
    "imagen": ""
  },
  {
    "id": "4244820_",
    "nombre": "Avellino vs Pescara",
    "imagen": ""
  },
  {
    "id": "4228763_",
    "nombre": "Alcorcón vs Real Murcia",
    "imagen": ""
  },
  {
    "id": "4240266_",
    "nombre": "Potenza vs Altamura",
    "imagen": ""
  },
  {
    "id": "4240651_",
    "nombre": "Lecco vs Virtus Verona",
    "imagen": ""
  },
  {
    "id": "4194658_",
    "nombre": "S. S. C. Napoli vs A. S. Roma",
    "imagen": ""
  },
  {
    "id": "4200293_",
    "nombre": "Olympique de Lyon vs O. G. C. Nice",
    "imagen": ""
  },
  {
    "id": "4209795_",
    "nombre": "RCD Mallorca vs Real Betis Balompié",
    "imagen": ""
  },
  {
    "id": "4212995_",
    "nombre": "Castellón vs Deportivo de La Coruña",
    "imagen": ""
  },
  {
    "id": "4321889_",
    "nombre": "Gimnasia LP vs Estudiantes LP",
    "imagen": ""
  },
  {
    "id": "4341344_",
    "nombre": "Comerciantes Unidos vs Los Chankas",
    "imagen": ""
  },
  {
    "id": "4216044_",
    "nombre": "Sporting CP vs Famalicao",
    "imagen": ""
  },
  {
    "id": "4319163_",
    "nombre": "Liberia vs Saprissa",
    "imagen": ""
  },
  {
    "id": "4331482_",
    "nombre": "Tolima vs Once Caldas",
    "imagen": ""
  },
  {
    "id": "4321881_",
    "nombre": "Boca Jrs vs Platense",
    "imagen": ""
  },
  {
    "id": "4322472_",
    "nombre": "Cruz Azul vs Tigres UANL",
    "imagen": ""
  },
  {
    "id": "4322449_",
    "nombre": "Santos Laguna vs Mazatlán",
    "imagen": ""
  },
  {
    "id": "4331485_",
    "nombre": "Deportivo Cali vs Atl. Nacional",
    "imagen": ""
  },
  {
    "id": "4341191_",
    "nombre": "Melgar vs Moquegua",
    "imagen": ""
  },
  {
    "id": "4353966_",
    "nombre": "Ypiranga FC vs Club deportivo internacional",
    "imagen": ""
  },
  {
    "id": "4319172_",
    "nombre": "Alajuelense vs Sporting San Jose",
    "imagen": ""
  },
  {
    "id": "4321894_",
    "nombre": "Instituto vs Central Córdoba",
    "imagen": ""
  },
  {
    "id": "4327470_",
    "nombre": "Rosario Central vs Barracas Central",
    "imagen": ""
  },
  {
    "id": "4325445_",
    "nombre": "Club América F vs Monterrey F",
    "imagen": ""
  },
  {
    "id": "4331491_",
    "nombre": "Fortaleza vs Boyacá Chicó",
    "imagen": ""
  }
]
