[
  {
    "id": "4324022_",
    "nombre": "Mirassol vs Cruzeiro Esporte Clube",
    "imagen": ""
  },
  {
    "id": "4335932_",
    "nombre": "Rosario Central vs Sportivo Belgrano",
    "imagen": ""
  },
  {
    "id": "4308319_",
    "nombre": "Sporting JAX W vs Spokane Zephyr W",
    "imagen": ""
  },
  {
    "id": "4327927_",
    "nombre": "Alianza Lima vs Club Sportivo 2 de Mayo",
    "imagen": ""
  },
  {
    "id": "4319422_",
    "nombre": "Club América vs Olimpia",
    "imagen": ""
  },
  {
    "id": "4336829_",
    "nombre": "El Salvador U17 vs CuracaoU17",
    "imagen": ""
  },
  {
    "id": "4336830_",
    "nombre": "Honduras U17 vs Bermuda U17",
    "imagen": ""
  },
  {
    "id": "4348602_",
    "nombre": "Real Estelí vs Diriangén",
    "imagen": ""
  },
  {
    "id": "4331467_",
    "nombre": "La Equidad vs Deportivo Cali",
    "imagen": ""
  },
  {
    "id": "4353516_",
    "nombre": "fafage banua vs kuda laut nusantara",
    "imagen": ""
  },
  {
    "id": "4319599_",
    "nombre": "Monterrey vs Xelajú",
    "imagen": ""
  }
]
